SpectralCARSLib/__init__.py
SpectralCARSLib/cars.py
SpectralCARSLib/classification.py
SpectralCARSLib/corcars.py
SpectralCARSLib/core.py
SpectralCARSLib/optimizer.py
SpectralCARSLib/preprocessing.py
SpectralCARSLib/simple_optimizer.py
SpectralCARSLib/utils.py
SpectralCARSLib/visualization.py
spectralcarslib-4.5.1.dist-info/licenses/LICENSE
spectralcarslib-4.5.1.dist-info/METADATA
spectralcarslib-4.5.1.dist-info/WHEEL
spectralcarslib-4.5.1.dist-info/top_level.txt
spectralcarslib-4.5.1.dist-info/RECORD
