Metadata-Version: 2.4
Name: SpectralCARSLib
Version: 4.5.1
Summary: Competitive Adaptive Reweighted Sampling family for variable selection in PLS
Home-page: https://github.com/Ginnovation-lab/SpectralCARSLib
Author: Special Research Unit of Big Data Analytics in Food, Agriculture and Health, Kasetsart University
Author-email: innovation.research.25@gmail.com
License: MIT
Classifier: Programming Language :: Python :: 3
Classifier: License :: OSI Approved :: MIT License
Classifier: Operating System :: OS Independent
Classifier: Topic :: Scientific/Engineering :: Chemistry
Classifier: Topic :: Scientific/Engineering :: Information Analysis
Classifier: Topic :: Scientific/Engineering :: Artificial Intelligence
Requires-Python: >=3.9
License-File: LICENSE
Requires-Dist: numpy>=1.19.0
Requires-Dist: scipy>=1.5.0
Requires-Dist: scikit-learn>=0.24.0
Requires-Dist: matplotlib>=3.3.0
Requires-Dist: joblib>=1.0.0
Requires-Dist: pandas>=1.1.0
Requires-Dist: seaborn>=0.11.0
Provides-Extra: optimizer
Requires-Dist: scikit-optimize>=0.9.0; extra == "optimizer"
Provides-Extra: dev
Requires-Dist: pytest; extra == "dev"
Requires-Dist: flake8; extra == "dev"
Requires-Dist: black; extra == "dev"
Requires-Dist: sphinx; extra == "dev"
Requires-Dist: sphinx_rtd_theme; extra == "dev"
Dynamic: author
Dynamic: author-email
Dynamic: classifier
Dynamic: description
Dynamic: description-content-type
Dynamic: home-page
Dynamic: license
Dynamic: license-file
Dynamic: provides-extra
Dynamic: requires-dist
Dynamic: requires-python
Dynamic: summary
